{
  "professions": {
    "弁護士": {
      "id": "lawyer",
      "name": "弁護士",
      "categoryId": "professional-specialized",
      "annualIncome": "500万円～2000万円以上",
      "jobDetails": "法律の専門家として、困っている人の権利を守るお仕事です。裁判で依頼人の代理人として活動したり、契約書をチェックしたり、法律相談に応じたりします。社会の正義を守り、法的なトラブルを解決する、とても重要で責任のある職業です。",
      "comment": "あなたは弁護士に向いているかもしれませんね！正義感が強く、困っている人を助けたいという気持ちがあるなら、とても向いています。論理的に物事を考えて、説得力のある主張ができるあなたなら、多くの人の権利と利益を守ることができるでしょう。社会に大きく貢献できる素晴らしいお仕事です。",
      "traits": [
        "強い正義感と倫理観を持っている",
        "論理的思考力と分析力に優れている",
        "困っている人を助けたいという使命感がある",
        "文章作成能力と語学力が高い",
        "プレッシャーに強く、責任感がある"
      ],
      "requiredSkills": [
        "法律知識・判例研究",
        "論理的思考・法的分析能力",
        "交渉・弁論技術",
        "文書作成・契約書チェック",
        "クライアント対応・相談業務"
      ],
      "careerPath": [
        "新人弁護士・法律事務所勤務（年収400-600万円）",
        "一般弁護士（年収500-1000万円）",
        "パートナー弁護士（年収800-1500万円）",
        "独立・法律事務所設立（年収1000-3000万円）",
        "企業法務・渉外弁護士（年収1500万円以上）"
      ],
      "workEnvironment": "法律事務所、企業の法務部、行政機関等。激務の場合もあるが、高い専門性と社会的地位を得られる。",
      "demandOutlook": "企業法務・国際取引の増加で需要は安定。特に専門分野を持つ弁護士は高収入を期待できる。",
      "relatedProfessions": ["司法書士", "行政書士", "税理士", "弁理士"],
      "educationRequirements": "司法試験合格後、司法修習（1年）の修了が必須。法科大学院修了または予備試験合格が必要。",
      "workStyle": "office",
      "difficultyLevel": 5,
      "stabilityLevel": 4,
      "averageWorkingHours": "10-12時間（案件により変動）",
      "stressLevel": 5,
      "creativityLevel": 3,
      "socialInteractionLevel": 4
    },
    "税理士": {
      "id": "tax-accountant",
      "name": "税理士",
      "categoryId": "professional-specialized",
      "annualIncome": "400万円～1500万円",
      "jobDetails": "税金に関する専門家として、個人や会社の税務をサポートするお仕事です。確定申告書を作成したり、税務相談に乗ったり、会計帳簿をチェックしたりします。複雑な税法を理解して、お客様が正しく税金を納められるよう支援する重要な役割です。",
      "comment": "あなたは税理士に向いているかもしれません！数字を扱うのが得意で、細かい作業にも集中して取り組めるなら、とても向いています。あなたの専門知識で、たくさんの人や会社が税務で困らないようサポートできる、とても価値のあるお仕事です。信頼関係も深く築けるでしょう。",
      "traits": [
        "数字や計算に強く、正確性を重視する",
        "税法や会計に深い興味がある",
        "責任感が強く、継続的に学習できる",
        "お客様との信頼関係を大切にする",
        "複雑な問題を整理して解決できる"
      ],
      "requiredSkills": [
        "税法・会計の専門知識",
        "税務申告書作成・税務相談",
        "会計ソフト・ITスキル",
        "経営アドバイス・コンサルティング",
        "クライアント対応・信頼関係構築"
      ],
      "careerPath": [
        "税理士事務所勤務（年収300-500万円）",
        "税理士・独立開業（年収500-800万円）",
        "顧客拡大・専門特化（年収700-1200万円）",
        "税理士法人設立・拡大（年収1000-2000万円）",
        "企業の税務責任者・顧問（年収1200万円以上）"
      ],
      "workEnvironment": "税理士事務所、会計事務所、企業の経理・財務部門、独立事務所等。確定申告時期は繁忙だが、やりがいがある。",
      "demandOutlook": "中小企業支援・相続税対策の需要で安定。特にデジタル化に対応できる税理士は高い需要がある。",
      "relatedProfessions": ["公認会計士", "中小企業診断士", "ファイナンシャルプランナー", "社会保険労務士"],
      "educationRequirements": "税理士試験（5科目）の合格が必要。実務経験2年以上も必要。簿記1級取得から始める人が多い。",
      "workStyle": "office",
      "difficultyLevel": 4,
      "stabilityLevel": 5,
      "averageWorkingHours": "8-9時間（繁忙期は長時間）",
      "stressLevel": 3,
      "creativityLevel": 2,
      "socialInteractionLevel": 4
    },
    "建築士": {
      "id": "architect",
      "name": "建築士",
      "categoryId": "professional-specialized",
      "annualIncome": "400万円～1000万円以上",
      "jobDetails": "住宅やビルなどの建物を設計するお仕事です。お客様の要望を聞いて、美しく機能的で安全な建物の図面を作成します。デザインだけでなく、構造や法規制も考慮して、みんなが安心して使える建物を生み出す、とてもクリエイティブで専門性の高い職業です。",
      "comment": "あなたは建築士に向いているかもしれませんね！美しい建物を見るのが好きで、空間をデザインすることに興味があるなら、とても向いています。あなたの設計した建物で、たくさんの人が快適に過ごし、街の景観も美しくなる。自分の作品が形に残る、とても素晴らしいお仕事です。",
      "traits": [
        "デザインセンスがあり、美的感覚に優れている",
        "空間や構造に対する理解力がある",
        "細かい図面作成に集中して取り組める",
        "お客様の要望を形にする創造力がある",
        "安全性と機能性を両立できる技術力がある"
      ],
      "requiredSkills": [
        "建築設計・製図技術",
        "CAD・BIM等の設計ソフト",
        "建築法規・構造計算",
        "プレゼンテーション・提案力",
        "プロジェクト管理・工程管理"
      ],
      "careerPath": [
        "設計事務所勤務・設計補助（年収300-450万円）",
        "一級建築士・主任設計者（年収450-700万円）",
        "設計チーフ・プロジェクトリーダー（年収600-900万円）",
        "独立・設計事務所設立（年収700-1500万円）",
        "大手設計事務所パートナー（年収1000万円以上）"
      ],
      "workEnvironment": "設計事務所、建設会社、ハウスメーカー、行政機関等。クリエイティブな環境で、チーム制作が基本。",
      "demandOutlook": "都市再開発・リノベーション需要で安定。特に省エネ・耐震設計のスキルを持つ建築士は高い需要がある。",
      "relatedProfessions": ["建設業", "インテリアデザイナー", "都市プランナー", "構造設計士"],
      "educationRequirements": "一級建築士・二級建築士の資格取得が必要。建築系大学・専門学校卒業後、実務経験を経て受験。",
      "workStyle": "office",
      "difficultyLevel": 4,
      "stabilityLevel": 4,
      "averageWorkingHours": "8-10時間（納期前は長時間労働）",
      "stressLevel": 4,
      "creativityLevel": 5,
      "socialInteractionLevel": 4
    },
    "行政書士": {
      "id": "administrative-lawyer",
      "name": "行政書士",
      "categoryId": "professional-specialized",
      "annualIncome": "300万円～800万円",
      "jobDetails": "官公署に提出する書類の作成や手続きを代行するお仕事です。許認可申請、会社設立、相続手続きなど、行政手続きの専門家として、個人や企業をサポートします。法律と行政のルールに詳しく、複雑な手続きを分かりやすく案内する重要な役割を担います。",
      "comment": "あなたは行政書士に向いているかもしれません！ルールや手続きを整理するのが得意で、困っている人を助けたいという気持ちがあるなら、とても向いています。複雑な行政手続きを分かりやすく案内して、お客様の負担を軽くできる、とても価値のあるお仕事です。",
      "traits": [
        "法律や行政手続きに興味がある",
        "細かい書類作成に正確に取り組める",
        "お客様の立場に立って親身に相談に乗れる",
        "複雑な手続きを分かりやすく説明できる",
        "継続的に法改正等の情報をキャッチアップできる"
      ],
      "requiredSkills": [
        "行政法・民法等の法律知識",
        "許認可申請・行政手続き",
        "書類作成・文書作成能力",
        "相談業務・カウンセリング",
        "コンピューター・電子申請システム"
      ],
      "careerPath": [
        "行政書士事務所勤務（年収250-400万円）",
        "行政書士・独立開業（年収300-600万円）",
        "専門分野特化・顧客拡大（年収500-800万円）",
        "行政書士法人設立（年収700-1200万円）",
        "企業の許認可担当・顧問（年収800万円以上）"
      ],
      "workEnvironment": "行政書士事務所、独立事務所、企業の総務・法務部門等。お客様との面談と書類作成が中心の仕事。",
      "demandOutlook": "規制緩和に伴う許認可業務で需要は安定。特に外国人雇用・国際業務に対応できる行政書士は高い需要がある。",
      "relatedProfessions": ["司法書士", "社会保険労務士", "税理士", "中小企業診断士"],
      "educationRequirements": "行政書士試験の合格が必要。法学部出身者が有利だが、他学部からの合格者も多い。実務経験も重視される。",
      "workStyle": "office",
      "difficultyLevel": 3,
      "stabilityLevel": 4,
      "averageWorkingHours": "8時間（独立の場合は変動）",
      "stressLevel": 2,
      "creativityLevel": 2,
      "socialInteractionLevel": 4
    }
  }
}